odoo/addons/ssi_psychology_evaluation_outsource_work/README.rst
odoo/addons/ssi_psychology_evaluation_outsource_work/__init__.py
odoo/addons/ssi_psychology_evaluation_outsource_work/__manifest__.py
odoo/addons/ssi_psychology_evaluation_outsource_work/models/__init__.py
odoo/addons/ssi_psychology_evaluation_outsource_work/models/psychology_evaluation.py
odoo/addons/ssi_psychology_evaluation_outsource_work/models/psychology_evaluation_type.py
odoo/addons/ssi_psychology_evaluation_outsource_work/static/description/icon.png
odoo/addons/ssi_psychology_evaluation_outsource_work/views/psychology_evaluation_type_views.xml
odoo/addons/ssi_psychology_evaluation_outsource_work/views/psychology_evaluation_views.xml
odoo14_addon_ssi_psychology_evaluation_outsource_work-14.0.1.1.0.dist-info/METADATA
odoo14_addon_ssi_psychology_evaluation_outsource_work-14.0.1.1.0.dist-info/WHEEL
odoo14_addon_ssi_psychology_evaluation_outsource_work-14.0.1.1.0.dist-info/top_level.txt
odoo14_addon_ssi_psychology_evaluation_outsource_work-14.0.1.1.0.dist-info/RECORD
